factom_core/__init__.py
factom_core/block_elements/__init__.py
factom_core/block_elements/admin_messages.py
factom_core/block_elements/balance_increase.py
factom_core/block_elements/chain.py
factom_core/block_elements/chain_commit.py
factom_core/block_elements/entry.py
factom_core/block_elements/entry_commit.py
factom_core/block_elements/factoid_transaction.py
factom_core/blockchains/__init__.py
factom_core/blockchains/base.py
factom_core/blockchains/pending_block.py
factom_core/blockchains/custom/__init__.py
factom_core/blockchains/custom/constants.py
factom_core/blockchains/local/__init__.py
factom_core/blockchains/local/constants.py
factom_core/blockchains/mainnet/__init__.py
factom_core/blockchains/mainnet/constants.py
factom_core/blockchains/mainnet/genesis.py
factom_core/blockchains/testnet/__init__.py
factom_core/blockchains/testnet/constants.py
factom_core/blockchains/testnet/genesis.py
factom_core/blocks/__init__.py
factom_core/blocks/admin_block.py
factom_core/blocks/directory_block.py
factom_core/blocks/entry_block.py
factom_core/blocks/entry_credit_block.py
factom_core/blocks/factoid_block.py
factom_core/db/__init__.py
factom_core/db/leveldb.py
factom_core/messages/__init__.py
factom_core/messages/ack.py
factom_core/messages/base.py
factom_core/messages/block_syncing.py
factom_core/messages/entry_syncing.py
factom_core/messages/heartbeat.py
factom_core/messages/missing_message.py
factom_core/messages/seals.py
factom_core/messages/server.py
factom_core/messages/transactions.py
factom_core/primitives/__init__.py
factom_core/primitives/signatures.py
factom_core/utils/__init__.py
factom_core/utils/filters.py
factom_core/utils/merkle.py
factom_core/utils/timestamp.py
factom_core/utils/varint.py
hydra/rpc/__init__.py
hydra/rpc/server.py
factom_core-0.0.9.dist-info/LICENSE
factom_core-0.0.9.dist-info/METADATA
factom_core-0.0.9.dist-info/WHEEL
factom_core-0.0.9.dist-info/top_level.txt
factom_core-0.0.9.dist-info/RECORD
